convertertools-0.6.1.dist-info/METADATA
convertertools-0.6.1.dist-info/RECORD
convertertools-0.6.1.dist-info/WHEEL
convertertools-0.6.1.dist-info/LICENSE
convertertools/py.typed
convertertools/__init__.py
convertertools/impl.py
convertertools/impl.cpython-311-i386-linux-gnu.so
