Metadata-Version: 2.3
Name: convertertools
Version: 0.6.1
Summary: Tools for converting python data types
License: MIT
Author: J. Nick Koston
Author-email: nick@koston.org
Requires-Python: >=3.10
Classifier: Development Status :: 2 - Pre-Alpha
Classifier: Intended Audience :: Developers
Classifier: License :: OSI Approved :: MIT License
Classifier: Natural Language :: English
Classifier: Operating System :: OS Independent
Classifier: Programming Language :: Python :: 3
Classifier: Programming Language :: Python :: 3.10
Classifier: Programming Language :: Python :: 3.11
Classifier: Programming Language :: Python :: 3.12
Classifier: Programming Language :: Python :: 3.13
Classifier: Topic :: Software Development :: Libraries
Project-URL: Bug Tracker, https://github.com/bluetooth-devices/convertertools/issues
Project-URL: Changelog, https://github.com/bluetooth-devices/convertertools/blob/main/CHANGELOG.md
Project-URL: Documentation, https://convertertools.readthedocs.io
Project-URL: Repository, https://github.com/bluetooth-devices/convertertools
